{"lock_version": 1, "external_documents": [], "extents": [], "jsonmodel_type": "archival_object", "ref_id": "ref3837_9vp", "instances": [{"lock_version": 0, "system_mtime": "2015-04-28T18:44:06Z", "container": {"lock_version": 0, "indicator_1": "22", "jsonmodel_type": "container", "user_mtime": "2014-12-07T13:44:41Z", "last_modified_by": "pgalligan", "container_locations": [{"status": "current", "system_mtime": "2014-12-07 13:44:41 UTC", "ref": "/locations/7784", "user_mtime": "2014-12-07 13:44:41 UTC", "start_date": "2014-12-05"}], "type_1": "reel", "create_time": "2014-12-07T13:44:41Z", "created_by": "pgalligan", "system_mtime": "2014-12-07T13:44:41Z"}, "jsonmodel_type": "instance", "user_mtime": "2014-12-07T13:44:41Z", "last_modified_by": "pgalligan", "instance_type": "Moving Images", "create_time": "2014-12-07T13:44:41Z", "created_by": "pgalligan"}, {"lock_version": 0, "system_mtime": "2014-12-07T19:35:45Z", "container": {"lock_version": 0, "indicator_1": "286a", "indicator_2": "3624", "jsonmodel_type": "container", "user_mtime": "2014-12-07T13:44:41Z", "last_modified_by": "pgalligan", "container_locations": [{"status": "current", "system_mtime": "2014-12-07 13:44:41 UTC", "ref": "/locations/2551", "user_mtime": "2014-12-07 13:44:41 UTC", "start_date": "2014-12-05"}], "type_2": "folder", "type_1": "box", "create_time": "2014-12-07T13:44:41Z", "created_by": "pgalligan", "system_mtime": "2014-12-07T13:44:41Z"}, "jsonmodel_type": "instance", "user_mtime": "2014-12-07T13:44:41Z", "last_modified_by": "pgalligan", "instance_type": "mixed materials", "create_time": "2014-12-07T13:44:41Z", "created_by": "pgalligan"}], "create_time": "2014-12-06T03:51:51Z", "created_by": "admin", "parent": {"ref": "/repositories/2/archival_objects/19204"}, "title": "The Angels of Serra Center - Arthur Zegart", "display_string": "The Angels of Serra Center - Arthur Zegart, probably 1970s", "publish": true, "subjects": [], "system_mtime": "2015-11-21T05:02:57Z", "linked_agents": [], "repository": {"ref": "/repositories/2"}, "repository_processing_note": "Accession number: 2006.113.22\n", "has_unpublished_ancestor": false, "user_mtime": "2014-12-07T13:44:41Z", "rights_statements": [], "linked_events": [], "external_ids": [{"system_mtime": "2014-12-07T13:44:41Z", "jsonmodel_type": "external_id", "user_mtime": "2014-12-07T13:44:41Z", "last_modified_by": "pgalligan", "source": "Archivists Toolkit Database::RESOURCE_COMPONENT", "create_time": "2014-12-07T13:44:41Z", "created_by": "pgalligan", "external_id": "76221"}], "suppressed": false, "dates": [{"lock_version": 0, "system_mtime": "2014-12-07T13:44:41Z", "begin": "1970", "end": "1979", "jsonmodel_type": "date", "date_type": "inclusive", "user_mtime": "2014-12-07T13:44:41Z", "last_modified_by": "pgalligan", "label": "creation", "create_time": "2014-12-07T13:44:41Z", "created_by": "pgalligan", "expression": "probably 1970s"}], "component_id": "2006.113.22", "resource": {"ref": "/repositories/2/resources/94"}, "level": "file", "notes": [{"jsonmodel_type": "note_singlepart", "persistent_id": "cb42c3c1d8791f653ff79ff7acd242e4", "publish": false, "label": "Physical Characteristics", "content": ["gauge/medium: 16 mm film\n\nbase: polyester\n\ncolor\n\nnegative: no\n\nsound: yes\n\nsound type: optical\n\ncode: SAFETY FILM 49 [] EASTMAN"], "type": "physdesc"}, {"jsonmodel_type": "note_singlepart", "persistent_id": "3d60688f0e6c2be60c63dd8e6eb2f16f", "publish": false, "label": "Physical Treatment", "content": ["wind: preservation\n\ndigitization recommendation: recommend film for digitization"], "type": "physdesc"}, {"jsonmodel_type": "note_singlepart", "persistent_id": "faa8e05fe5104c97cfc11720e0fb7ed9", "publish": false, "label": "Physical Condition", "content": ["sound: good\n\nemulsion scratches: no\n\nbase scratches: no\n\npreforation damage: no\n\nshrinkage: no\n\ncolor fading: yes (magenta hue)\n\nvinegar syndrome: no\n\nother condition notes: n/a"], "type": "physdesc"}, {"subnotes": [{"content": "Produced, directed and written by Arthur Zegart, Serra Residential Center, Freemont, California\n\nProduced in association with the National Council of Churches", "publish": true, "jsonmodel_type": "note_text"}], "jsonmodel_type": "note_multipart", "persistent_id": "834810be30bf1fb263918e05de4273f5", "publish": true, "label": "Credits", "type": "scopecontent"}, {"subnotes": [{"content": "Documentary footage at the Serra Residential Center. Focuses on adults with mental disabilities and mental retardation, and the center's efforts to support the integration of these adults into the Freemont, California community.", "publish": true, "jsonmodel_type": "note_text"}], "jsonmodel_type": "note_multipart", "persistent_id": "3613347c795db854a62c260ee11e726b", "publish": true, "label": "Subjects", "type": "scopecontent"}, {"type": "dimensions", "persistent_id": "0083e14f85250beb8a708a2adefc8fec", "subnotes": [{"content": "approximately 900 feet", "publish": true, "jsonmodel_type": "note_text"}], "jsonmodel_type": "note_multipart", "publish": true}, {"type": "accessrestrict", "persistent_id": "3419b8d4f22a4096f43505fb790ff77d", "subnotes": [{"content": "RAC is unable to provide access to obsolete media and original digital media. In addition separated media may not yet have undergone stabilization procedures. When feasible, a digital surrogate may be created via special order. All applicable charges will apply. See RAC Head of Archival Services or RAC Head of Digital Programs for details.\n\n", "publish": true, "jsonmodel_type": "note_text"}], "jsonmodel_type": "note_multipart", "publish": true}, {"jsonmodel_type": "note_singlepart", "persistent_id": "ccb36fcd9a7bf6227a779f7b644855b3", "publish": true, "label": "Container Summary", "content": ["1 reel and 1 folder of supplemental material "], "type": "physdesc"}], "uri": "/repositories/2/archival_objects/19226", "last_modified_by": "pgalligan", "restrictions_apply": false, "position": 21}