{"lock_version": 0, "system_mtime": "2015-11-21T05:12:22Z", "extents": [], "jsonmodel_type": "archival_object", "ref_id": "ref6720_u7p", "instances": [{"lock_version": 0, "system_mtime": "2014-12-07T19:35:45Z", "container": {"lock_version": 0, "indicator_1": "37", "indicator_2": "306", "jsonmodel_type": "container", "user_mtime": "2014-12-06T04:08:34Z", "last_modified_by": "admin", "container_locations": [], "type_2": "folder", "type_1": "box", "create_time": "2014-12-06T04:08:34Z", "created_by": "admin", "system_mtime": "2014-12-06T04:08:34Z"}, "jsonmodel_type": "instance", "user_mtime": "2014-12-06T04:08:34Z", "last_modified_by": "admin", "instance_type": "mixed materials", "create_time": "2014-12-06T04:08:34Z", "created_by": "admin"}], "create_time": "2014-12-06T04:08:34Z", "created_by": "admin", "parent": {"ref": "/repositories/2/archival_objects/32301"}, "title": "National Social Welfare Assembly", "display_string": "National Social Welfare Assembly, 1946-1947", "publish": true, "subjects": [], "external_documents": [], "linked_agents": [], "repository": {"ref": "/repositories/2"}, "has_unpublished_ancestor": false, "user_mtime": "2014-12-06T04:08:34Z", "rights_statements": [], "linked_events": [], "external_ids": [{"system_mtime": "2014-12-06T04:08:34Z", "jsonmodel_type": "external_id", "user_mtime": "2014-12-06T04:08:34Z", "last_modified_by": "admin", "source": "Archivists Toolkit Database::RESOURCE_COMPONENT", "create_time": "2014-12-06T04:08:34Z", "created_by": "admin", "external_id": "1255413"}], "suppressed": false, "dates": [{"lock_version": 0, "system_mtime": "2014-12-06T04:08:34Z", "begin": "1946", "end": "1947", "jsonmodel_type": "date", "date_type": "inclusive", "user_mtime": "2014-12-06T04:08:34Z", "last_modified_by": "admin", "label": "creation", "create_time": "2014-12-06T04:08:34Z", "created_by": "admin", "expression": "1946-1947"}], "resource": {"ref": "/repositories/2/resources/103"}, "level": "file", "notes": [{"subnotes": [{"content": "2088\n\n", "publish": true, "jsonmodel_type": "note_text"}], "jsonmodel_type": "note_multipart", "persistent_id": "12f245950c49c8dacd0b0cab59929b01", "publish": true, "label": "File Plan note", "type": "fileplan"}, {"subnotes": [{"content": "RSF grant money; information on Association.\n\n", "publish": true, "jsonmodel_type": "note_text"}], "jsonmodel_type": "note_multipart", "persistent_id": "94e69ab64ecf731f8e2570172662f6ff", "publish": true, "label": "Scope and Contents note", "type": "scopecontent"}], "uri": "/repositories/2/archival_objects/32592", "last_modified_by": "admin", "restrictions_apply": false, "position": 290}