{"lock_version": 2, "external_documents": [], "extents": [{"lock_version": 0, "system_mtime": "2015-09-26T17:10:30Z", "jsonmodel_type": "extent", "user_mtime": "2015-09-26T17:10:30Z", "number": "0.2", "last_modified_by": "battalb", "container_summary": "0.25 Box", "portion": "whole", "create_time": "2015-09-26T17:10:30Z", "created_by": "battalb", "extent_type": "cubic_feet"}], "jsonmodel_type": "archival_object", "ref_id": "ref1348_8gk", "instances": [], "create_time": "2014-12-06T04:08:49Z", "created_by": "admin", "parent": {"ref": "/repositories/2/archival_objects/32268"}, "title": "Miscellaneous Reports and Proposals", "display_string": "Miscellaneous Reports and Proposals, 1967, 1972, undated", "publish": true, "subjects": [], "system_mtime": "2015-11-21T05:12:18Z", "linked_agents": [], "repository": {"ref": "/repositories/2"}, "repository_processing_note": "Processed by Melissa A. Smith, January, 1988\n", "has_unpublished_ancestor": false, "user_mtime": "2015-09-26T17:10:30Z", "rights_statements": [], "linked_events": [], "external_ids": [{"system_mtime": "2015-09-26T17:10:30Z", "jsonmodel_type": "external_id", "user_mtime": "2015-09-26T17:10:30Z", "last_modified_by": "battalb", "source": "Archivists Toolkit Database::RESOURCE_COMPONENT", "create_time": "2015-09-26T17:10:30Z", "created_by": "battalb", "external_id": "25501"}], "suppressed": false, "dates": [{"lock_version": 0, "system_mtime": "2015-09-26T17:10:30Z", "begin": "1967", "end": "1972", "jsonmodel_type": "date", "date_type": "inclusive", "user_mtime": "2015-09-26T17:10:30Z", "last_modified_by": "battalb", "label": "creation", "create_time": "2015-09-26T17:10:30Z", "created_by": "battalb", "expression": "1967, 1972, undated"}], "component_id": "7", "resource": {"ref": "/repositories/2/resources/103"}, "level": "series", "notes": [{"subnotes": [{"content": "This series contains five reports or proposals on various topics. Four of them were written by either Orville Brim or Wilbert Moore.\n\n", "publish": true, "jsonmodel_type": "note_text"}], "jsonmodel_type": "note_multipart", "persistent_id": "561666efd1d64308d156a4d411060b22", "publish": true, "label": "Scope and Contents note", "type": "scopecontent"}], "uri": "/repositories/2/archival_objects/32880", "last_modified_by": "battalb", "restrictions_apply": false, "position": 6}