{"lock_version": 0, "system_mtime": "2015-11-21T05:14:14Z", "extents": [{"lock_version": 0, "system_mtime": "2014-12-06T04:21:35Z", "jsonmodel_type": "extent", "user_mtime": "2014-12-06T04:21:35Z", "number": "7.2", "last_modified_by": "admin", "portion": "whole", "create_time": "2014-12-06T04:21:35Z", "created_by": "admin", "extent_type": "cubic_feet"}], "jsonmodel_type": "archival_object", "ref_id": "ref1856_ni1", "instances": [], "create_time": "2014-12-06T04:21:35Z", "created_by": "admin", "parent": {"ref": "/repositories/2/archival_objects/40626"}, "title": "Committee on Problems and Policy - Minutes", "display_string": "Committee on Problems and Policy - Minutes, 1925-1985", "publish": true, "subjects": [], "external_documents": [], "linked_agents": [], "repository": {"ref": "/repositories/2"}, "has_unpublished_ancestor": false, "user_mtime": "2014-12-06T04:21:35Z", "rights_statements": [], "linked_events": [], "external_ids": [{"system_mtime": "2014-12-06T04:21:35Z", "jsonmodel_type": "external_id", "user_mtime": "2014-12-06T04:21:35Z", "last_modified_by": "admin", "source": "Archivists Toolkit Database::RESOURCE_COMPONENT", "create_time": "2014-12-06T04:21:35Z", "created_by": "admin", "external_id": "38869"}], "suppressed": false, "dates": [{"lock_version": 0, "system_mtime": "2014-12-06T04:21:35Z", "begin": "1925", "end": "1985", "jsonmodel_type": "date", "date_type": "inclusive", "user_mtime": "2014-12-06T04:21:35Z", "last_modified_by": "admin", "label": "creation", "create_time": "2014-12-06T04:21:35Z", "created_by": "admin", "expression": "1925-1985"}], "component_id": "2", "resource": {"ref": "/repositories/2/resources/109"}, "level": "series", "notes": [{"persistent_id": "98509b202718d932cce8b598f9f2d91d", "type": "altformavail", "subnotes": [{"content": "Scholarly access to original archival material is permitted.  User copies of microfilm are also available.", "publish": true, "jsonmodel_type": "note_text"}], "jsonmodel_type": "note_multipart", "publish": true}, {"subnotes": [{"content": "The Committee on Problems and Policy is the Council's central planning body and was formed in 1925. The committee is a group of elected scholars who review the programs of the working committees that carry out the Council's programs. Members of the committee are drawn primarily from college and university faculties. This series consists of the minutes of this committee.\n\n", "publish": true, "jsonmodel_type": "note_text"}], "jsonmodel_type": "note_multipart", "persistent_id": "c01276f762dc73593e15952df9dd7480", "publish": true, "label": "Scope and Contents note", "type": "scopecontent"}], "uri": "/repositories/2/archival_objects/42458", "last_modified_by": "admin", "restrictions_apply": false, "position": 1}