{"lock_version": 0, "system_mtime": "2015-11-21T05:00:11Z", "extents": [], "jsonmodel_type": "archival_object", "ref_id": "ref1159_tdp", "instances": [{"lock_version": 0, "system_mtime": "2015-09-23T18:30:30Z", "container": {"lock_version": 0, "indicator_1": "49", "jsonmodel_type": "container", "user_mtime": "2014-12-06T03:31:08Z", "last_modified_by": "admin", "container_locations": [], "type_1": "box", "create_time": "2014-12-06T03:31:08Z", "created_by": "admin", "system_mtime": "2014-12-06T03:31:08Z"}, "jsonmodel_type": "instance", "user_mtime": "2014-12-06T03:31:08Z", "last_modified_by": "admin", "instance_type": "Still Image", "create_time": "2014-12-06T03:31:08Z", "created_by": "admin"}], "create_time": "2014-12-06T03:31:08Z", "created_by": "admin", "parent": {"ref": "/repositories/2/archival_objects/4769"}, "title": "Photograph 2922H1", "display_string": "Photograph 2922H1", "publish": true, "subjects": [], "external_documents": [], "linked_agents": [], "repository": {"ref": "/repositories/2"}, "has_unpublished_ancestor": true, "user_mtime": "2014-12-06T03:31:08Z", "rights_statements": [], "linked_events": [], "external_ids": [{"system_mtime": "2014-12-06T03:31:08Z", "jsonmodel_type": "external_id", "user_mtime": "2014-12-06T03:31:08Z", "last_modified_by": "admin", "source": "Archivists Toolkit Database::RESOURCE_COMPONENT", "create_time": "2014-12-06T03:31:08Z", "created_by": "admin", "external_id": "1511619"}], "suppressed": false, "dates": [], "component_id": "2012:083:108", "resource": {"ref": "/repositories/2/resources/20"}, "level": "item", "notes": [{"jsonmodel_type": "note_singlepart", "persistent_id": "dad91521f6051bcc47d83a6d999a4df4", "publish": true, "label": "Container Summary", "content": ["1 photograph - 8 x 10\""], "type": "physdesc"}], "uri": "/repositories/2/archival_objects/4770", "last_modified_by": "admin", "restrictions_apply": false, "position": 0}