{"lock_version": 1, "system_mtime": "2016-02-05T17:56:00Z", "extents": [], "jsonmodel_type": "archival_object", "ref_id": "ref12_haq", "instances": [{"lock_version": 0, "system_mtime": "2016-02-05T17:56:00Z", "container": {"lock_version": 0, "indicator_1": "SF 1", "jsonmodel_type": "container", "barcode_1": "A0000000016513", "container_extent_type": "cubic_feet", "user_mtime": "2016-02-05T17:56:00Z", "last_modified_by": "jwelby", "container_locations": [], "type_1": "box", "create_time": "2016-02-05T17:56:00Z", "created_by": "jwelby", "container_extent": ".22", "system_mtime": "2016-02-05T17:56:00Z"}, "jsonmodel_type": "instance", "user_mtime": "2016-02-05T17:56:00Z", "last_modified_by": "jwelby", "instance_type": "mixed materials", "create_time": "2016-02-05T17:56:00Z", "created_by": "jwelby"}], "create_time": "2014-12-06T03:33:04Z", "created_by": "admin", "parent": {"ref": "/repositories/2/archival_objects/6390"}, "title": "Still Images", "display_string": "Still Images", "publish": true, "subjects": [], "external_documents": [], "linked_agents": [], "repository": {"ref": "/repositories/2"}, "has_unpublished_ancestor": true, "user_mtime": "2016-02-05T17:56:00Z", "rights_statements": [], "linked_events": [], "external_ids": [{"system_mtime": "2016-02-05T17:56:00Z", "jsonmodel_type": "external_id", "user_mtime": "2016-02-05T17:56:00Z", "last_modified_by": "jwelby", "source": "Archivists Toolkit Database::RESOURCE_COMPONENT", "create_time": "2016-02-05T17:56:00Z", "created_by": "jwelby", "external_id": "1283629"}], "suppressed": false, "dates": [], "component_id": "2013:074:001", "resource": {"ref": "/repositories/2/resources/34"}, "level": "item", "notes": [{"jsonmodel_type": "note_singlepart", "persistent_id": "3871037e87b42040bf3cfafed847eed9", "publish": true, "label": "Container Summary", "content": ["7 sheets of still image slides"], "type": "physdesc"}], "uri": "/repositories/2/archival_objects/6391", "last_modified_by": "jwelby", "restrictions_apply": false, "position": 0}