{"lock_version": 1, "external_documents": [], "extents": [], "jsonmodel_type": "archival_object", "ref_id": "ref29_b44", "instances": [], "create_time": "2014-12-06T03:34:03Z", "created_by": "admin", "parent": {"ref": "/repositories/2/archival_objects/6982"}, "title": "Chassin Disk Recieved 1/24/05", "display_string": "Chassin Disk Recieved 1/24/05", "publish": true, "subjects": [], "system_mtime": "2015-11-21T05:00:31Z", "linked_agents": [], "repository": {"ref": "/repositories/2"}, "repository_processing_note": "1 3.5 Floppy Disk\n", "has_unpublished_ancestor": true, "user_mtime": "2014-12-07T13:01:22Z", "rights_statements": [], "linked_events": [], "external_ids": [{"system_mtime": "2014-12-07T13:01:22Z", "jsonmodel_type": "external_id", "user_mtime": "2014-12-07T13:01:22Z", "last_modified_by": "pgalligan", "source": "Archivists Toolkit Database::RESOURCE_COMPONENT", "create_time": "2014-12-07T13:01:22Z", "created_by": "pgalligan", "external_id": "1511787"}], "suppressed": false, "dates": [], "component_id": "2013.093.001", "resource": {"ref": "/repositories/2/resources/46"}, "level": "item", "notes": [{"jsonmodel_type": "note_singlepart", "persistent_id": "c1927d741f00470d598c3cd49e5aed6c", "publish": true, "label": "Container Summary", "content": ["Digital Material"], "type": "physdesc"}], "uri": "/repositories/2/archival_objects/6983", "last_modified_by": "pgalligan", "restrictions_apply": false, "position": 0}