{"lock_version": 0, "system_mtime": "2015-11-21T05:00:45Z", "extents": [], "jsonmodel_type": "archival_object", "ref_id": "ref29_811", "instances": [], "create_time": "2014-12-06T03:36:36Z", "created_by": "admin", "parent": {"ref": "/repositories/2/archival_objects/8278"}, "title": "[20225k]", "display_string": "[20225k]", "publish": true, "subjects": [], "external_documents": [], "linked_agents": [], "repository": {"ref": "/repositories/2"}, "has_unpublished_ancestor": true, "user_mtime": "2014-12-06T03:36:36Z", "rights_statements": [], "linked_events": [], "external_ids": [{"system_mtime": "2014-12-06T03:36:36Z", "jsonmodel_type": "external_id", "user_mtime": "2014-12-06T03:36:36Z", "last_modified_by": "admin", "source": "Archivists Toolkit Database::RESOURCE_COMPONENT", "create_time": "2014-12-06T03:36:36Z", "created_by": "admin", "external_id": "1817630"}], "suppressed": false, "dates": [], "component_id": "2014.063.027", "resource": {"ref": "/repositories/2/resources/81"}, "level": "item", "notes": [{"jsonmodel_type": "note_singlepart", "persistent_id": "1c288910cd90c375d0fcb5da3a1ac7ba", "publish": true, "label": "Container Summary", "content": ["Still Image"], "type": "physdesc"}], "uri": "/repositories/2/archival_objects/8302", "last_modified_by": "admin", "restrictions_apply": false, "position": 23}